sudoku_solver-0.2.data/scripts/sudoku_backtrack
sudoku_solver-0.2.data/scripts/sudoku_indexes
sudoku_solver-0.2.data/scripts/sudoku_solver
sudoku_solver-0.2.data/scripts/sudoku_solver_benchmark
sudoku_solver-0.2.dist-info/DESCRIPTION.rst
sudoku_solver-0.2.dist-info/METADATA
sudoku_solver-0.2.dist-info/RECORD
sudoku_solver-0.2.dist-info/WHEEL
sudoku_solver-0.2.dist-info/metadata.json
sudoku_solver-0.2.dist-info/top_level.txt
sudokulib/__init__.py
sudokulib/backtracking.py
sudokulib/constants.py
sudokulib/grid.py
sudokulib/layer.py
sudokulib/solver.py
sudokulib/preprocessors/__init__.py
sudokulib/preprocessors/block_block.py
sudokulib/preprocessors/disjoint_chain.py
sudokulib/preprocessors/line_block.py
sudokulib/preprocessors/naked_subset.py
sudokulib/solvers/__init__.py
sudokulib/solvers/hidden_singleton.py
sudokulib/solvers/naked_singleton.py
sudokulib/solvers/singleton.py
sudokulib/tests/__init__.py
sudokulib/tests/backtracking.py
sudokulib/tests/grid.py
sudokulib/tests/layer.py
sudokulib/tests/preprocessors.py
sudokulib/tests/solver.py
sudokulib/tests/solvers.py
