Metadata-Version: 2.0
Name: sudoku-solver
Version: 0.2
Summary: Library and scripts for solving Sudoku puzzles.
Home-page: http://github.com/Fantomas42/sudoku-solver
Author: Fantomas42
Author-email: fantomas42@gmail.com
License: BSD License
Keywords: sudoku,solver
Platform: any
Classifier: Operating System :: OS Independent
Classifier: Programming Language :: Python :: 2.7
Classifier: Programming Language :: Python :: 3
Classifier: Topic :: Software Development :: Libraries :: Python Modules
